tensorboard_termplot/__init__.py
tensorboard_termplot/main.py
tensorboard_termplot/backend/__init__.py
tensorboard_termplot/backend/base_plotter.py
tensorboard_termplot/backend/matplotlib_plot.py
tensorboard_termplot/backend/terminal_plot.py
tensorboard_termplot/data_source/__init__.py
tensorboard_termplot/data_source/csv_source.py
tensorboard_termplot/data_source/tensorboard_source.py
tensorboard_termplot-1.3.2.dist-info/LICENSE
tensorboard_termplot-1.3.2.dist-info/METADATA
tensorboard_termplot-1.3.2.dist-info/WHEEL
tensorboard_termplot-1.3.2.dist-info/entry_points.txt
tensorboard_termplot-1.3.2.dist-info/top_level.txt
tensorboard_termplot-1.3.2.dist-info/RECORD
