Metadata-Version: 2.1
Name: tensorboard-termplot
Version: 1.3.2
Summary: View tensorboard stats inside terminal.
Home-page: https://github.com/soraxas/tensorboard-termplot
Author: Tin Lai (@soraxas)
Author-email: oscar@tinyiu.com
License: MIT
Keywords: tui tensorboard termplot stats
Platform: UNKNOWN
Classifier: Environment :: Console
Classifier: Framework :: Matplotlib
Classifier: Intended Audience :: Developers
Classifier: Intended Audience :: End Users/Desktop
Classifier: Intended Audience :: System Administrators
Classifier: License :: OSI Approved :: MIT License
Classifier: Operating System :: MacOS
Classifier: Operating System :: POSIX
Classifier: Operating System :: Unix
Classifier: Programming Language :: Python :: 3.6
Classifier: Programming Language :: Python :: 3.7
Classifier: Programming Language :: Python :: 3.8
Classifier: Programming Language :: Python :: 3.9
Classifier: Topic :: Desktop Environment
Classifier: Topic :: Terminals
Classifier: Topic :: Utilities
Requires-Python: >=3.6
License-File: LICENSE
Requires-Dist: tensorboard (>=2.5)
Requires-Dist: plotext (==4.0)
Requires-Dist: mock
Requires-Dist: pillow
Requires-Dist: pandas
Requires-Dist: numpy
Requires-Dist: scipy
Provides-Extra: matplotlib-backend
Requires-Dist: matplotlib ; extra == 'matplotlib-backend'
